{
  "lastUpdate": "2026-05-15 16:29 UTC",
  "watchdogStatus": "OK",
  "workspaces": {
    "crypto_live": {
      "label": "Crypto BTC",
      "broker": "Aster DEX",
      "status": "live",
      "initialBalance": 518.65,
      "actionMap": {
        "0": "SHORT 2x",
        "1": "SHORT 1x",
        "2": "CASH",
        "3": "LONG 1x",
        "4": "LONG 2x"
      },
      "cashSignal": 2,
      "balance": 526.56,
      "freeCash": 367.97157816,
      "lastInference": "2026-05-15 17:10:08",
      "positions": {
        "BTC": {
          "entry_price": 75220.6,
          "current_price": 79120.0,
          "shares": 0.002,
          "alloc": 183.99,
          "leverage": "1.0x",
          "sl": 71459.57,
          "tp": 82742.66
        }
      },
      "lastPrices": {},
      "modelVersion": "legacy",
      "modelType": "PPO",
      "timeframe": "1d",
      "backtest": {
        "sharpe": null,
        "returnPct": null,
        "maxDD": null
      },
      "equityCurve": [
        {
          "d": "Start",
          "v": 518.65
        },
        {
          "d": "Apr 20",
          "v": 520.28
        },
        {
          "d": "Apr 21",
          "v": 519.44
        },
        {
          "d": "Apr 22",
          "v": 526.77
        },
        {
          "d": "Apr 23",
          "v": 525.15
        },
        {
          "d": "Apr 24",
          "v": 524.44
        },
        {
          "d": "Apr 25",
          "v": 524.18
        },
        {
          "d": "Apr 26",
          "v": 525.84
        },
        {
          "d": "Apr 27",
          "v": 522.7
        },
        {
          "d": "Apr 28",
          "v": 521.23
        },
        {
          "d": "Apr 29",
          "v": 520.06
        },
        {
          "d": "Apr 30",
          "v": 521.28
        },
        {
          "d": "May 1",
          "v": 525.37
        },
        {
          "d": "May 2",
          "v": 526.57
        },
        {
          "d": "May 3",
          "v": 527.62
        },
        {
          "d": "May 4",
          "v": 530.71
        },
        {
          "d": "May 5",
          "v": 533.85
        },
        {
          "d": "May 6",
          "v": 533.79
        },
        {
          "d": "May 7",
          "v": 530.05
        },
        {
          "d": "May 8",
          "v": 530.73
        },
        {
          "d": "May 9",
          "v": 532.21
        },
        {
          "d": "May 10",
          "v": 532.27
        },
        {
          "d": "May 11",
          "v": 534.22
        },
        {
          "d": "May 12",
          "v": 531.86
        },
        {
          "d": "May 13",
          "v": 528.81
        },
        {
          "d": "May 14",
          "v": 533.72
        },
        {
          "d": "May 15",
          "v": 528.19
        }
      ],
      "tradeCount": 0,
      "openPositions": 1,
      "tradingStartDate": "2026-04-20",
      "tradingDays": 25,
      "tradeStats": {
        "totalRows": 1214,
        "tradesWithPnl": 1213,
        "winRate": 99.3,
        "bestPct": 9.87,
        "worstPct": -0.52,
        "avgWinPct": 4.85,
        "avgLossPct": -0.18,
        "biggestWinVal": 14.84,
        "biggestLossVal": -1.17,
        "totalPnlVal": 7.91
      },
      "trades": [
        {
          "time": "2026-05-15 17:30:03",
          "ticker": "BTC",
          "signal": "LONG 1x",
          "entry": 75220.6,
          "current": 79120.0,
          "pnl": 5.18
        },
        {
          "time": "2026-05-15 17:10:10",
          "ticker": "BTC",
          "signal": "LONG 1x",
          "entry": 75220.6,
          "current": 79231.0,
          "pnl": 5.33
        },
        {
          "time": "2026-05-15 17:10:04",
          "ticker": "BTC",
          "signal": "LONG 1x",
          "entry": 75220.6,
          "current": 79232.1,
          "pnl": 5.33
        },
        {
          "time": "2026-05-15 16:30:03",
          "ticker": "BTC",
          "signal": "LONG 1x",
          "entry": 75220.6,
          "current": 79072.4,
          "pnl": 5.12
        },
        {
          "time": "2026-05-15 15:30:02",
          "ticker": "BTC",
          "signal": "LONG 1x",
          "entry": 75220.6,
          "current": 79977.6,
          "pnl": 6.32
        },
        {
          "time": "2026-05-15 15:10:10",
          "ticker": "BTC",
          "signal": "LONG 1x",
          "entry": 75220.6,
          "current": 80058.9,
          "pnl": 6.43
        },
        {
          "time": "2026-05-15 15:10:04",
          "ticker": "BTC",
          "signal": "LONG 1x",
          "entry": 75220.6,
          "current": 80064.02167753,
          "pnl": 6.44
        },
        {
          "time": "2026-05-15 14:30:03",
          "ticker": "BTC",
          "signal": "LONG 1x",
          "entry": 75220.6,
          "current": 80499.93044565,
          "pnl": 7.02
        },
        {
          "time": "2026-05-15 13:30:02",
          "ticker": "BTC",
          "signal": "LONG 1x",
          "entry": 75220.6,
          "current": 80591.49306522,
          "pnl": 7.14
        },
        {
          "time": "2026-05-15 13:10:11",
          "ticker": "BTC",
          "signal": "LONG 1x",
          "entry": 75220.6,
          "current": 80563.9,
          "pnl": 7.1
        }
      ]
    },
    "stocks": {
      "label": "Stocks (Dow 20)",
      "broker": "Alpaca Paper",
      "status": "paper",
      "initialBalance": 10000.0,
      "actionMap": {
        "0": "CASH",
        "1": "LONG 1x",
        "2": "LONG 1.5x"
      },
      "cashSignal": 0,
      "balance": 9906.61,
      "freeCash": 9406.58,
      "lastInference": "2026-05-15 14:00:15",
      "positions": {
        "AAPL": 1,
        "AMGN": 0,
        "AXP": 0,
        "BA": 0,
        "CAT": 0,
        "CRM": 0,
        "CSCO": 0,
        "CVX": 0,
        "DIS": 0,
        "GS": 0,
        "HD": 0,
        "HON": 0,
        "IBM": 0,
        "JNJ": 0,
        "JPM": 0,
        "KO": 0,
        "MCD": 0,
        "MMM": 0,
        "MSFT": 0,
        "WMT": 0
      },
      "lastPrices": {
        "AAPL": 301.175,
        "AMGN": 327.9699,
        "AXP": 313.47,
        "BA": 222.6,
        "CAT": 885.2328,
        "CRM": 173.61,
        "CSCO": 116.43,
        "CVX": 188.92,
        "DIS": 103.22,
        "GS": 951.755,
        "HD": 299.49,
        "HON": 212.05,
        "IBM": 218.79,
        "JNJ": 228.315,
        "JPM": 297.39,
        "KO": 80.735,
        "MCD": 276.105,
        "MMM": 145.645,
        "MSFT": 422.05,
        "WMT": 131.34
      },
      "modelVersion": "traditional_1d_v8_dd_control",
      "modelCreatedDate": "2026-04-25",
      "deployedAt": "2026-04-25 12:00:00",
      "baselineAtDeploy": 10000.0,
      "modelType": "DQN",
      "timeframe": "1d",
      "backtest": {
        "sharpe": 1.8834883184070652,
        "returnPct": 77.96888848034196,
        "maxDD": 11.69362127464361
      },
      "equityCurve": [
        {
          "d": "Start",
          "v": 10000.0
        },
        {
          "d": "Apr 27",
          "v": 9968.74
        },
        {
          "d": "Apr 28",
          "v": 9970.43
        },
        {
          "d": "Apr 29",
          "v": 9906.56
        },
        {
          "d": "Apr 30",
          "v": 10080.42
        },
        {
          "d": "May 1",
          "v": 10084.76
        },
        {
          "d": "May 4",
          "v": 9960.43
        },
        {
          "d": "May 5",
          "v": 10000.55
        },
        {
          "d": "May 6",
          "v": 10096.15
        },
        {
          "d": "May 7",
          "v": 10037.58
        },
        {
          "d": "May 8",
          "v": 10018.9
        },
        {
          "d": "May 11",
          "v": 10009.57
        },
        {
          "d": "May 12",
          "v": 10000.0
        },
        {
          "d": "May 13",
          "v": 10000.0
        },
        {
          "d": "May 14",
          "v": 10000.0
        },
        {
          "d": "May 15",
          "v": 10005.06
        }
      ],
      "tradeCount": 0,
      "openPositions": 16,
      "tradingStartDate": "2026-04-27",
      "tradingDays": 18,
      "tradeStats": {
        "totalRows": 579,
        "tradesWithPnl": 496,
        "winRate": 43.5,
        "bestPct": 11.66,
        "worstPct": -7.37,
        "avgWinPct": 2.63,
        "avgLossPct": -1.68,
        "biggestWinVal": 78.5,
        "biggestLossVal": -51.49,
        "totalPnlVal": -93.39
      },
      "trades": [
        {
          "time": "2026-05-15 18:00:16",
          "ticker": "AAPL",
          "signal": "LONG 1x",
          "entry": 298.21,
          "current": 301.225,
          "pnl": 1.01
        },
        {
          "time": "2026-05-15 18:00:12",
          "ticker": "PORTFOLIO",
          "signal": "CASH",
          "entry": 0.0,
          "current": 0.0,
          "pnl": 0.0
        },
        {
          "time": "2026-05-15 17:45:07",
          "ticker": "PORTFOLIO",
          "signal": "CASH",
          "entry": 0.0,
          "current": 0.0,
          "pnl": 0.0
        },
        {
          "time": "2026-05-15 16:45:07",
          "ticker": "PORTFOLIO",
          "signal": "CASH",
          "entry": 0.0,
          "current": 0.0,
          "pnl": 0.0
        },
        {
          "time": "2026-05-15 16:00:31",
          "ticker": "AAPL",
          "signal": "LONG 1x",
          "entry": 298.21,
          "current": 298.21,
          "pnl": 0.0
        },
        {
          "time": "2026-05-15 16:00:15",
          "ticker": "PORTFOLIO",
          "signal": "CASH",
          "entry": 0.0,
          "current": 0.0,
          "pnl": 0.0
        },
        {
          "time": "2026-05-15 15:45:08",
          "ticker": "PORTFOLIO",
          "signal": "CASH",
          "entry": 0.0,
          "current": 0.0,
          "pnl": 0.0
        },
        {
          "time": "2026-05-15 14:45:06",
          "ticker": "PORTFOLIO",
          "signal": "CASH",
          "entry": 0.0,
          "current": 0.0,
          "pnl": 0.0
        },
        {
          "time": "2026-05-15 13:45:07",
          "ticker": "PORTFOLIO",
          "signal": "CASH",
          "entry": 0.0,
          "current": 0.0,
          "pnl": 0.0
        },
        {
          "time": "2026-05-15 12:45:07",
          "ticker": "PORTFOLIO",
          "signal": "CASH",
          "entry": 0.0,
          "current": 0.0,
          "pnl": 0.0
        }
      ],
      "candidateVersion": "traditional_1d_v14_dd_control_reset"
    },
    "crypto_btc": {
      "label": "Crypto BTC",
      "broker": "Alpaca Paper",
      "status": "paper",
      "initialBalance": 10000.0,
      "actionMap": {
        "0": "SHORT 2x",
        "1": "SHORT 1x",
        "2": "CASH",
        "3": "LONG 1x",
        "4": "LONG 2x"
      },
      "cashSignal": 2,
      "balance": 9870.5,
      "freeCash": 3226.59,
      "lastInference": "2026-05-15 00:00:09",
      "positions": {
        "BTC": 4
      },
      "lastPrices": {
        "BTC": 79156.9375
      },
      "modelVersion": "btc_1d_v11_dd_sharp_balance",
      "modelCreatedDate": "2026-05-08",
      "deployedAt": "2026-05-12 10:00:16",
      "baselineAtDeploy": 9995.71,
      "modelType": "DQN",
      "timeframe": "1d",
      "backtest": {
        "sharpe": 1.684134405176096,
        "returnPct": 225.5192310661455,
        "maxDD": 31.96777418707229
      },
      "equityCurve": [
        {
          "d": "Start",
          "v": 10000.0
        },
        {
          "d": "May 2",
          "v": 10000.0
        },
        {
          "d": "May 3",
          "v": 10000.0
        },
        {
          "d": "May 4",
          "v": 10000.0
        },
        {
          "d": "May 5",
          "v": 10000.0
        },
        {
          "d": "May 6",
          "v": 10000.0
        },
        {
          "d": "May 7",
          "v": 10000.0
        },
        {
          "d": "May 8",
          "v": 10000.0
        },
        {
          "d": "May 9",
          "v": 10000.0
        },
        {
          "d": "May 10",
          "v": 10000.0
        },
        {
          "d": "May 11",
          "v": 10000.0
        },
        {
          "d": "May 12",
          "v": 10000.0
        },
        {
          "d": "May 13",
          "v": 10000.0
        },
        {
          "d": "May 14",
          "v": 10000.0
        },
        {
          "d": "May 15",
          "v": 9988.77
        }
      ],
      "tradeCount": 0,
      "openPositions": 1,
      "tradingStartDate": "2026-05-02",
      "tradingDays": 12,
      "tradeStats": {
        "totalRows": 199,
        "tradesWithPnl": 9,
        "winRate": 11.1,
        "bestPct": 0.06,
        "worstPct": -2.26,
        "avgWinPct": 0.06,
        "avgLossPct": -0.67,
        "biggestWinVal": 0.91,
        "biggestLossVal": -135.51,
        "totalPnlVal": -129.5
      },
      "trades": [
        {
          "time": "2026-05-15 18:15:04",
          "ticker": "PORTFOLIO",
          "signal": "CASH",
          "entry": 0.0,
          "current": 0.0,
          "pnl": 0.0
        },
        {
          "time": "2026-05-15 18:00:10",
          "ticker": "BTC",
          "signal": "LONG 2x",
          "entry": 80384.307227006,
          "current": 79180.758,
          "pnl": -1.5
        },
        {
          "time": "2026-05-15 18:00:06",
          "ticker": "PORTFOLIO",
          "signal": "CASH",
          "entry": 0.0,
          "current": 0.0,
          "pnl": 0.0
        },
        {
          "time": "2026-05-15 17:15:03",
          "ticker": "PORTFOLIO",
          "signal": "CASH",
          "entry": 0.0,
          "current": 0.0,
          "pnl": 0.0
        },
        {
          "time": "2026-05-15 16:15:03",
          "ticker": "PORTFOLIO",
          "signal": "CASH",
          "entry": 0.0,
          "current": 0.0,
          "pnl": 0.0
        },
        {
          "time": "2026-05-15 16:00:11",
          "ticker": "BTC",
          "signal": "LONG 2x",
          "entry": 80539.077186174,
          "current": 78721.22,
          "pnl": -2.26
        },
        {
          "time": "2026-05-15 16:00:08",
          "ticker": "PORTFOLIO",
          "signal": "CASH",
          "entry": 0.0,
          "current": 0.0,
          "pnl": 0.0
        },
        {
          "time": "2026-05-15 15:15:04",
          "ticker": "PORTFOLIO",
          "signal": "CASH",
          "entry": 0.0,
          "current": 0.0,
          "pnl": 0.0
        },
        {
          "time": "2026-05-15 14:15:04",
          "ticker": "PORTFOLIO",
          "signal": "CASH",
          "entry": 0.0,
          "current": 0.0,
          "pnl": 0.0
        },
        {
          "time": "2026-05-15 14:00:10",
          "ticker": "BTC",
          "signal": "LONG 2x",
          "entry": 80807.570855119,
          "current": 80692.5,
          "pnl": -0.14
        }
      ],
      "candidateVersion": "btc_1d_v13_sharpe_peak_refinement"
    },
    "crypto_multi": {
      "label": "Crypto Multi (5)",
      "broker": "Alpaca Paper",
      "status": "paper",
      "initialBalance": 10000.0,
      "actionMap": {
        "0": "SHORT 2x",
        "1": "SHORT 1x",
        "2": "CASH",
        "3": "LONG 1x",
        "4": "LONG 2x"
      },
      "cashSignal": 2,
      "balance": 9572.74,
      "freeCash": 8070.68,
      "lastInference": "2026-05-15 12:30:09",
      "positions": {
        "BTC": 4,
        "ETH": 0,
        "AVAX": 1,
        "LINK": 4,
        "DOGE": 2
      },
      "lastPrices": {
        "BTC": 79063.4609,
        "ETH": 2217.4199,
        "AVAX": 9.47,
        "LINK": 10.0,
        "DOGE": 0.111
      },
      "modelVersion": "4h_v9_sharpe_peak_extended_features",
      "modelCreatedDate": "2026-05-05",
      "deployedAt": "2026-05-05 12:00:00",
      "baselineAtDeploy": 10000.0,
      "modelType": "DQN",
      "timeframe": "4h",
      "backtest": {
        "sharpe": 3.216511729650261,
        "returnPct": 72.3435887099924,
        "maxDD": 12.234016081660936
      },
      "equityCurve": [
        {
          "d": "Start",
          "v": 10000.0
        },
        {
          "d": "May 2",
          "v": 10000.0
        },
        {
          "d": "May 3",
          "v": 9996.55
        },
        {
          "d": "May 4",
          "v": 9990.32
        },
        {
          "d": "May 5",
          "v": 10035.1
        },
        {
          "d": "May 6",
          "v": 10039.73
        },
        {
          "d": "May 7",
          "v": 9976.8
        },
        {
          "d": "May 8",
          "v": 9973.62
        },
        {
          "d": "May 9",
          "v": 10000.0
        },
        {
          "d": "May 10",
          "v": 10000.0
        },
        {
          "d": "May 11",
          "v": 10000.0
        },
        {
          "d": "May 12",
          "v": 10002.9
        },
        {
          "d": "May 13",
          "v": 10002.15
        },
        {
          "d": "May 14",
          "v": 9996.62
        },
        {
          "d": "May 15",
          "v": 9963.72
        }
      ],
      "tradeCount": 0,
      "openPositions": 5,
      "tradingStartDate": "2026-05-02",
      "tradingDays": 12,
      "tradeStats": {
        "totalRows": 316,
        "tradesWithPnl": 137,
        "winRate": 43.1,
        "bestPct": 6.62,
        "worstPct": -3.47,
        "avgWinPct": 1.4,
        "avgLossPct": -0.81,
        "biggestWinVal": 46.56,
        "biggestLossVal": -26.93,
        "totalPnlVal": -427.26
      },
      "trades": [
        {
          "time": "2026-05-15 17:45:05",
          "ticker": "PORTFOLIO",
          "signal": "CASH",
          "entry": 0.0,
          "current": 0.0,
          "pnl": 0.0
        },
        {
          "time": "2026-05-15 16:30:14",
          "ticker": "LINK",
          "signal": "LONG 2x",
          "entry": 10.369486561,
          "current": 10.01,
          "pnl": -3.47
        },
        {
          "time": "2026-05-15 16:30:14",
          "ticker": "BTC",
          "signal": "LONG 2x",
          "entry": 80884.305906769,
          "current": 79018.353,
          "pnl": -2.31
        },
        {
          "time": "2026-05-15 16:30:11",
          "ticker": "PORTFOLIO",
          "signal": "CASH",
          "entry": 0.0,
          "current": 0.0,
          "pnl": 0.0
        },
        {
          "time": "2026-05-15 15:45:05",
          "ticker": "PORTFOLIO",
          "signal": "CASH",
          "entry": 0.0,
          "current": 0.0,
          "pnl": 0.0
        },
        {
          "time": "2026-05-15 14:30:16",
          "ticker": "LINK",
          "signal": "LONG 2x",
          "entry": 10.380742594,
          "current": 10.3028,
          "pnl": -0.75
        },
        {
          "time": "2026-05-15 14:30:16",
          "ticker": "BTC",
          "signal": "LONG 2x",
          "entry": 80929.03,
          "current": 80471.5,
          "pnl": -0.57
        },
        {
          "time": "2026-05-15 14:30:09",
          "ticker": "PORTFOLIO",
          "signal": "CASH",
          "entry": 0.0,
          "current": 0.0,
          "pnl": 0.0
        },
        {
          "time": "2026-05-15 13:45:05",
          "ticker": "PORTFOLIO",
          "signal": "CASH",
          "entry": 0.0,
          "current": 0.0,
          "pnl": 0.0
        },
        {
          "time": "2026-05-15 12:30:10",
          "ticker": "LINK",
          "signal": "LONG 2x",
          "entry": 10.380742594,
          "current": 10.3024,
          "pnl": -0.75
        }
      ],
      "candidateVersion": "4h_v12_sharpe_peak_recovery_feature_rollback"
    }
  },
  "strategy": {
    "totalExperiments": 24,
    "lastRun": "2026-05-15T10:00:45.155246",
    "schedule": "Tue/Fri 08:00 UTC",
    "pipelines": {
      "crypto_btc": {
        "status": "waiting_results",
        "experiment": "btc_1d_v13_sharpe_peak_refinement",
        "paperStart": "2026-05-12",
        "failures": 1
      },
      "crypto_multi": {
        "status": "waiting_results",
        "experiment": "4h_v12_sharpe_peak_recovery_feature_rollback",
        "paperStart": "2026-05-08",
        "failures": 2
      },
      "stocks": {
        "status": "waiting_results",
        "experiment": "traditional_1d_v14_dd_control_reset",
        "paperStart": "2026-04-28",
        "failures": 2
      }
    }
  }
}